swh/webhooks/__init__.py
swh/webhooks/cli.py
swh/webhooks/interface.py
swh/webhooks/journal_client.py
swh/webhooks/py.typed
swh/webhooks/svix_retry.py
swh/webhooks/utils.py
swh/webhooks/event_types/origin_create.json
swh/webhooks/event_types/origin_visit.json
swh/webhooks/tests/__init__.py
swh/webhooks/tests/conftest.py
swh/webhooks/tests/docker-compose.yml
swh/webhooks/tests/svix.env
swh/webhooks/tests/test_cli.py
swh/webhooks/tests/test_journal_client.py
swh/webhooks/tests/test_svix_retry.py
swh/webhooks/tests/test_utils.py
swh/webhooks/tests/test_webhooks.py
swh/webhooks/tests/data/origin_create.json
swh/webhooks/tests/data/origin_visit.json
swh_webhooks-0.3.2.dist-info/licenses/AUTHORS
swh_webhooks-0.3.2.dist-info/licenses/LICENSE
swh_webhooks-0.3.2.dist-info/METADATA
swh_webhooks-0.3.2.dist-info/WHEEL
swh_webhooks-0.3.2.dist-info/entry_points.txt
swh_webhooks-0.3.2.dist-info/top_level.txt
swh_webhooks-0.3.2.dist-info/RECORD
