Metadata-Version: 2.4
Name: swh.webhooks
Version: 0.3.2
Summary: Software Heritage Webhooks management
Author-email: Software Heritage developers <swh-devel@inria.fr>
Project-URL: Homepage, https://gitlab.softwareheritage.org/swh/devel/swh-webhooks
Project-URL: Bug Reports, https://gitlab.softwareheritage.org/swh/devel/swh-webhooks/-/issues
Project-URL: Funding, https://www.softwareheritage.org/donate
Project-URL: Documentation, https://docs.softwareheritage.org/devel/swh-webhooks/
Project-URL: Source, https://gitlab.softwareheritage.org/swh/devel/swh-webhooks.git
Classifier: Programming Language :: Python :: 3
Classifier: Intended Audience :: Developers
Classifier: License :: OSI Approved :: GNU General Public License v3 (GPLv3)
Classifier: Operating System :: OS Independent
Classifier: Development Status :: 3 - Alpha
Requires-Python: >=3.7
License-File: LICENSE
License-File: AUTHORS
Requires-Dist: click
Requires-Dist: jsonschema[format]
Requires-Dist: svix==1.62.0
Requires-Dist: tenacity>=8.4.2
Requires-Dist: typing-extensions
Requires-Dist: swh.core
Requires-Dist: swh.journal>=2.0.0
Provides-Extra: testing
Requires-Dist: netifaces; extra == "testing"
Requires-Dist: pytest>=8.1; extra == "testing"
Requires-Dist: pytest-click; extra == "testing"
Requires-Dist: pytest-docker; extra == "testing"
Requires-Dist: pytest-httpserver; extra == "testing"
Requires-Dist: pytest-mock; extra == "testing"
Requires-Dist: swh.journal[pytest]>=2.0.0; extra == "testing"
Requires-Dist: types-jsonschema; extra == "testing"
Requires-Dist: types-netifaces; extra == "testing"
Requires-Dist: types-PyYAML; extra == "testing"
Requires-Dist: types-requests; extra == "testing"
Requires-Dist: types-urllib3; extra == "testing"
Dynamic: license-file
